klfuncutil/__init__.py
klfuncutil/collection.py
klfuncutil/iterator.py
klfuncutil-1.0.2.dist-info/LICENSE
klfuncutil-1.0.2.dist-info/WHEEL
klfuncutil-1.0.2.dist-info/METADATA
klfuncutil-1.0.2.dist-info/RECORD
