Metadata-Version: 2.3
Name: klfuncutil
Version: 1.0.2
Summary: Utilities for functional programming
Author-email: Robert Kaltenthaler <nuuk42@yahoo.com>
Classifier: License :: OSI Approved :: MIT License
Classifier: Programming Language :: Python :: 3
